sphinx_veldus_ext/__init__.py
sphinx_veldus_ext/azgaar_map/__init__.py
sphinx_veldus_ext/azgaar_map/azgaar-map.html
sphinx_veldus_ext/azgaar_map/css/azgaar-map.css
sphinx_veldus_ext/npc_statblock/__init__.py
sphinx_veldus_ext/npc_statblock/npc.html
sphinx_veldus_ext/npc_statblock/summary-table.html
sphinx_veldus_ext/place_statblock/__init__.py
sphinx_veldus_ext/place_statblock/place.html
sphinx_veldus_ext/place_statblock/summary-table.html
sphinx_veldus_ext-0.2.12.dist-info/METADATA
sphinx_veldus_ext-0.2.12.dist-info/WHEEL
sphinx_veldus_ext-0.2.12.dist-info/licenses/LICENSE
sphinx_veldus_ext-0.2.12.dist-info/RECORD
